commons_imaging/__init__.py
commons_imaging/image_info.py
commons_imaging/imaging.py
commons_imaging-0.1.0.dist-info/METADATA
commons_imaging-0.1.0.dist-info/WHEEL
commons_imaging-0.1.0.dist-info/RECORD
